{
    "swagger": "2.0",
    "info": {
        "description": "Illustration of uncle Bob's clean architecture using a demo blogs api.\nIt serves as Blog.",
        "title": "ACTSML Gin Gonic golang Clean Architecture Orchestrator.",
        "contact": {},
        "version": "1.0"
    },
    "host": "localhost:8080",
    "basePath": "/api/v1",
    "paths": {
        "/jobs/create": {
            "post": {
                "description": "Create a Kubernetes training job",
                "consumes": [
                    "application/json"
                ],
                "produces": [
                    "application/json"
                ],
                "tags": [
                    "Job"
                ],
                "summary": "Create a Job",
                "operationId": "Create a Job",
                "parameters": [
                    {
                        "description": "Job payload (raw JSON)",
                        "name": "request",
                        "in": "body",
                        "required": true,
                        "schema": {
                            "type": "object"
                        }
                    }
                ],
                "responses": {
                    "202": {
                        "description": "Accepted",
                        "schema": {
                            "$ref": "#/definitions/job_route.createJobResponse"
                        }
                    },
                    "400": {
                        "description": "Bad Request",
                        "schema": {
                            "$ref": "#/definitions/entity.HTTPError"
                        }
                    },
                    "500": {
                        "description": "Internal Server Error",
                        "schema": {
                            "$ref": "#/definitions/entity.HTTPError"
                        }
                    }
                }
            }
        },
        "/jobs/{id}/status": {
            "get": {
                "description": "Get status of a Kubernetes training job",
                "produces": [
                    "application/json"
                ],
                "tags": [
                    "Job"
                ],
                "summary": "Get Job Status",
                "operationId": "Get Job Status",
                "parameters": [
                    {
                        "type": "string",
                        "description": "Job ID (actsml-job-{uuid})",
                        "name": "id",
                        "in": "path",
                        "required": true
                    }
                ],
                "responses": {
                    "200": {
                        "description": "OK",
                        "schema": {
                            "$ref": "#/definitions/job_route.getJobStatusResponse"
                        }
                    },
                    "404": {
                        "description": "Not Found",
                        "schema": {
                            "$ref": "#/definitions/entity.HTTPError"
                        }
                    },
                    "500": {
                        "description": "Internal Server Error",
                        "schema": {
                            "$ref": "#/definitions/entity.HTTPError"
                        }
                    }
                }
            }
        }
    },
    "definitions": {
        "entity.HTTPError": {
            "type": "object",
            "properties": {
                "code": {
                    "type": "integer"
                },
                "message": {
                    "type": "string"
                }
            }
        },
        "job_route.createJobResponse": {
            "type": "object",
            "properties": {
                "experiment_id": {
                    "type": "string"
                },
                "job_id": {
                    "type": "string"
                },
                "k8s_job_name": {
                    "type": "string"
                },
                "project_id": {
                    "type": "string"
                },
                "status": {
                    "type": "string"
                },
                "submitted_at": {
                    "type": "string"
                }
            }
        },
        "job_route.getJobStatusResponse": {
            "type": "object",
            "properties": {
                "job_id": {
                    "type": "string"
                },
                "k8s_conditions": {},
                "status": {
                    "type": "string"
                }
            }
        }
    },
    "securityDefinitions": {
        "BasicAuth": {
            "type": "basic"
        }
    }
}